{
  "$schema": "https://json-schema.org/draft/2020-12/schema",
  "$id": "superclaw.action_receipt.v0",
  "type": "object",
  "additionalProperties": false,
  "required": [
    "schema",
    "receipt_id",
    "action_id",
    "trace_id",
    "request_id",
    "created_at",
    "principal_id",
    "org_id",
    "customer_tenant_id",
    "isolation_cell_id",
    "capability_hash",
    "policy_decision_id",
    "policy_effect",
    "effective_data_classes",
    "prev_receipt_hash",
    "receipt_hash",
    "signed_by",
    "signature"
  ],
  "properties": {
    "schema": { "const": "superclaw.action_receipt.v0" },
    "receipt_id": { "type": "string" },
    "action_id": { "type": "string" },
    "trace_id": { "type": "string" },
    "request_id": { "type": "string" },
    "created_at": { "type": "string" },
    "principal_id": { "type": "string" },
    "org_id": { "type": "string" },
    "customer_tenant_id": { "type": "string" },
    "isolation_cell_id": { "type": "string" },
    "namespace_id": { "type": "string" },
    "runtime_pool_id": { "type": "string" },
    "capability_hash": { "type": "string" },
    "policy_decision_id": { "type": "string" },
    "policy_effect": { "enum": ["allow", "deny"] },
    "effective_data_classes": { "type": "array", "items": { "type": "string" } },
    "resource_refs": { "type": "array", "items": { "type": "string" } },
    "memory_read_set": { "type": "array", "items": { "type": "string" } },
    "memory_write_set": { "type": "array", "items": { "type": "string" } },
    "tool_identity": { "type": "string" },
    "platform_receipt_ref": { "type": "string" },
    "redaction_profile": { "type": "string" },
    "prev_receipt_hash": { "type": "string" },
    "receipt_hash": { "type": "string" },
    "signed_by": { "type": "string" },
    "signature": { "type": "string" }
  }
}
